Metadata-Version: 2.1
Name: dbt-light
Version: 1.0.0
Summary: Lightweight data build tool
Home-page: https://github.com/DenisKudr/dbt_light
Author: Denis Kudryavtsev
Author-email: denizkudryavtsev@yandex.ru
License: Apache License 2.0
Platform: UNKNOWN
Requires-Python: >=3.8.10
Requires-Dist: PyYAML (~=6.0)
Requires-Dist: Jinja2 (~=3.0.3)
Requires-Dist: psycopg2 (~=2.9.3)
Requires-Dist: setuptools (~=57.0.0)
Requires-Dist: schema (~=0.7.5)
